{
  "project_info": {
    "project_number": "933912472043",
    "project_id": "diarybycompose",
    "storage_bucket": "diarybycompose.appspot.com"
  },
  "client": [
    {
      "client_info": {
        "mobilesdk_app_id": "1:933912472043:android:0f836fc4c60b31ebc1d1ae",
        "android_client_info": {
          "package_name": "com.jm.diarybycompose"
        }
      },
      "oauth_client": [],
      "api_key": [
        {
          "current_key": "AIzaSyCkSOwC2piKWvbBdYNAEQInYYu4D6ZhNdU"
        }
      ],
      "services": {
        "appinvite_service": {
          "other_platform_oauth_client": []
        }
      }
    }
  ],
  "configuration_version": "1"
}